{"current_re": ["master", "node", "fwdd", "member", "pfem", "re0", "fpc0", "localre"], "domain": null, "fqdn": "access-sw2", "switch_style": "VLAN_L2NG", "HOME": "/var/home/automation", "srx_cluster": null, "srx_cluster_id": null, "srx_cluster_redundancy_group": null, "RE_hw_mi": false, "serialnumber": "10031410755", "master": "RE0", "RE0": {"mastership_state": "master", "status": "Absent", "model": "QFX Routing Engine", "last_reboot_reason": "Router rebooted after a normal shutdown.", "up_time": "22 hours, 38 minutes, 1 second"}, "RE1": null, "re_info": {"default": {"0": {"mastership_state": "master", "status": "Absent", "model": "QFX Routing Engine", "last_reboot_reason": "Router rebooted after a normal shutdown."}, "default": {"mastership_state": "master", "status": "Absent", "model": "QFX Routing Engine", "last_reboot_reason": "Router rebooted after a normal shutdown."}}}, "re_master": {"default": "0"}, "junos_info": {"fpc0": {"text": "19.4R1.10", "object": {"major": [19, 4], "type": "R", "minor": "1", "build": 10}}}, "hostname": "access-sw2", "hostname_info": {"fpc0": "access-sw2"}, "model": "VQFX-10000", "model_info": {"fpc0": "VQFX-10000"}, "version": "19.4R1.10", "version_info": {"major": [19, 4], "type": "R", "minor": "1", "build": 10}, "version_RE0": null, "version_RE1": null, "vc_capable": true, "vc_mode": "Enabled", "vc_fabric": false, "vc_master": "0", "ifd_style": "CLASSIC", "personality": null, "virtual": null, "re_name": "fpc0", "master_state": true, "has_2RE": false}